fsds/__init__.py
fsds/datasets.py
fsds/default.py
fsds/fsds.py
fsds/imports.py
fsds/imports_legacy.py
fsds/quick_refs.py
fsds/041320PT/__init__.py
fsds/070620FT/__init__.py
fsds/jmi/__init__.py
fsds/jmi/jmi.py
fsds/jmi/jmi_WIP.py
fsds/pandemic/__init__.py
fsds/pandemic/coronavirus_functions.py
fsds/pandemic/data_acquisition.py
fsds/pandemic/legacy_data_acquisition.py
fsds/pandemic/timeseries_modeling.py
fsds-0.4.14.dist-info/AUTHORS.rst
fsds-0.4.14.dist-info/LICENSE
fsds-0.4.14.dist-info/METADATA
fsds-0.4.14.dist-info/WHEEL
fsds-0.4.14.dist-info/top_level.txt
fsds-0.4.14.dist-info/RECORD
