Metadata-Version: 2.1
Name: fsds
Version: 0.4.14
Summary: Cohort agnostic version of fsds_100719 package
Home-page: https://github.com/jirvingphd/fsds
Author: James Irving
Author-email: james.irving.phd@gmail.com
License: GNU General Public License v3
Keywords: fsds
Platform: UNKNOWN
Classifier: Development Status :: 2 - Pre-Alpha
Classifier: Intended Audience :: Developers
Classifier: License :: OSI Approved :: GNU General Public License v3 (GPLv3)
Classifier: Natural Language :: English
Classifier: Programming Language :: Python :: 3
Classifier: Programming Language :: Python :: 3.7
Classifier: Programming Language :: Python :: 3.8
Requires-Python: >=3.7
License-File: LICENSE
License-File: AUTHORS.rst
Requires-Dist: numpy (>=1.18.5)
Requires-Dist: missingno
Requires-Dist: pandas (>=1.1.3)
Requires-Dist: seaborn (>=0.11.0)
Requires-Dist: matplotlib (>=3.2.2)
Requires-Dist: scikit-learn (>=0.23.1)
Requires-Dist: scipy
Requires-Dist: IPython
Requires-Dist: ipywidgets
Requires-Dist: tzlocal
Requires-Dist: pyperclip
Requires-Dist: plotly (>=4.0.0)
Requires-Dist: cufflinks (>=0.17.0)
